_p2pExtension.cpython-39-i386-linux-gnu.so
spatial_access/BaseModel.py
spatial_access/__init__.py
spatial_access/_parsers.py
spatial_access/Models.py
spatial_access/Configs.py
spatial_access/NetworkInterface.py
spatial_access/SpatialAccessExceptions.py
spatial_access/p2p.py
spatial_access/MatrixInterface.py
travel_time-1.0.2.dist-info/METADATA
travel_time-1.0.2.dist-info/WHEEL
travel_time-1.0.2.dist-info/RECORD
travel_time-1.0.2.dist-info/LICENSE
travel_time-1.0.2.dist-info/top_level.txt
