Metadata-Version: 2.1
Name: travel_time
Version: 1.0.2
Summary: UNKNOWN
Home-page: https://github.com/lixun910/travel_time
Author: Logan Noel (lmnoel), Xun Li
Author-email: lnoel@uchicago.edu
License: GPL
Platform: UNKNOWN
License-File: LICENSE
